<document xmlns:xsi="http://www.w3.org/2001/XMLSchema-instance" xsi:noNamespaceSchemaLocation="../petriflow_schema.xsd">
    <id>dynamic_validations</id>
    <title>dynamic_validations</title>
    <defaultRole>true</defaultRole>
    <initials>DVT</initials>
    <!-- ROLES -->
    <data type="number">
        <id>min</id>
        <title>Min</title>
    </data>
    <data type="number">
        <id>max</id>
        <title>Max</title>
        <init>5</init>
    </data>
    <data type="number">
        <id>number</id>
        <title>Number</title>
        <validations>
            <validation>
                <expression>inrange ${min.value},${max.value}</expression>
                <message>Number field validation message</message>
            </validation>
        </validations>
    </data>

    <data type="boolean">
        <id>bool_switch</id>
        <title>Switch</title>

        <action trigger="set">
            bool_switch: f.bool_switch,
            number: f.number;

            if (bool_switch.value) {
                change number validations { "odd" }
            } else {
                change number validations { '''inrange ${min.value},${max.value}''' }
            }
        </action>
    </data>

    <transition>
        <id>transition</id>
        <x>200</x>
        <y>200</y>
        <label>Transition</label>
        <assignPolicy>auto</assignPolicy>

        <dataRef>
            <id>min</id>
            <logic>
                <behavior>editable</behavior>
            </logic>
        </dataRef><dataRef>
            <id>max</id>
            <logic>
                <behavior>editable</behavior>
            </logic>
        </dataRef>
        <dataRef>
            <id>number</id>
            <logic>
                <behavior>editable</behavior>
            </logic>
        </dataRef>
        <dataRef>
            <id>bool_switch</id>
            <logic>
                <behavior>editable</behavior>
            </logic>
        </dataRef>
    </transition>

</document>